tresor/__init__.py
tresor/gcell/FromSimulator.py
tresor/gcell/__init__.py
tresor/gcell/deepcvaesc/Predict.py
tresor/gcell/deepcvaesc/__init__.py
tresor/gene.py
tresor/gmat.py
tresor/gsample/FromSimulator.py
tresor/gsample/__init__.py
tresor/library/Gene.py
tresor/library/SingleCell.py
tresor/library/SingleLocus.py
tresor/library/UMIDouble.py
tresor/library/__init__.py
tresor/locus.py
tresor/main.py
tresor/path.py
tresor/pcr/Amplify.py
tresor/pcr/Error.py
tresor/pcr/Subsampling.py
tresor/pcr/__init__.py
tresor/read/Library.py
tresor/read/__init__.py
tresor/read/adapter/Design.py
tresor/read/adapter/__init__.py
tresor/read/barcode/Design.py
tresor/read/barcode/__init__.py
tresor/read/error/Library.py
tresor/read/error/__init__.py
tresor/read/inf/Pseudo.py
tresor/read/inf/__init__.py
tresor/read/primer/Design.py
tresor/read/primer/__init__.py
tresor/read/seq/Design.py
tresor/read/seq/__init__.py
tresor/read/spacer/Design.py
tresor/read/spacer/__init__.py
tresor/read/umi/Design.py
tresor/read/umi/__init__.py
tresor/sc.py
tresor/scenario/__init__.py
tresor/scenario/amplrate/Gene.py
tresor/scenario/amplrate/SingleCell.py
tresor/scenario/amplrate/SingleLocus.py
tresor/scenario/amplrate/__init__.py
tresor/scenario/generic/SingleLocus.py
tresor/scenario/generic/__init__.py
tresor/scenario/pcrerr/Gene.py
tresor/scenario/pcrerr/SingleCell.py
tresor/scenario/pcrerr/SingleLocus.py
tresor/scenario/pcrerr/__init__.py
tresor/scenario/pcrnum/Gene.py
tresor/scenario/pcrnum/SingleCell.py
tresor/scenario/pcrnum/SingleLocus.py
tresor/scenario/pcrnum/__init__.py
tresor/scenario/seqdep/Gene.py
tresor/scenario/seqdep/SingleCell.py
tresor/scenario/seqdep/SingleLocus.py
tresor/scenario/seqdep/__init__.py
tresor/scenario/seqerr/Gene.py
tresor/scenario/seqerr/SingleCell.py
tresor/scenario/seqerr/SingleLocus.py
tresor/scenario/seqerr/__init__.py
tresor/scenario/umilen/Gene.py
tresor/scenario/umilen/SingleCell.py
tresor/scenario/umilen/SingleLocus.py
tresor/scenario/umilen/__init__.py
tresor-0.1.2.dist-info/LICENSE
tresor-0.1.2.dist-info/METADATA
tresor-0.1.2.dist-info/WHEEL
tresor-0.1.2.dist-info/RECORD
