Metadata-Version: 2.3
Name: tresor
Version: 0.1.2
Summary: 
Author: Jianfeng Sun
Author-email: jianfeng.sunmt@gmail.com
Requires-Python: >=3.11,<4.0
Classifier: Programming Language :: Python :: 3
Classifier: Programming Language :: Python :: 3.11
Classifier: Programming Language :: Python :: 3.12
Classifier: Programming Language :: Python :: 3.13
Requires-Dist: biopython (>=1.84,<2.0)
Requires-Dist: click (>=8.1.7,<9.0.0)
Requires-Dist: numpy (>=2.0.0,<3.0.0)
Requires-Dist: pandas (>=2.2.2,<3.0.0)
Requires-Dist: pyfastx (>=2.1.0,<3.0.0)
Requires-Dist: pyfiglet (>=1.0.2,<2.0.0)
Requires-Dist: pyyaml (>=6.0.1,<7.0.0)
Requires-Dist: scipy (>=1.14.0,<2.0.0)
